yjs/__init__.py
yjs-0.0.2.dist-info/METADATA
yjs-0.0.2.dist-info/WHEEL
yjs-0.0.2.dist-info/entry_points.txt
yjs-0.0.2.dist-info/top_level.txt
yjs-0.0.2.dist-info/RECORD
