Metadata-Version: 2.1
Name: yjs
Version: 0.0.2
Summary: 云计算，永远的家
Home-page: https://91yjs.ml
Author: yjs
Author-email: yjs@gmail.com
License: UNKNOWN
Platform: UNKNOWN
Requires-Dist: requests
